jsonschema_fill_default/__init__.py
jsonschema_fill_default/jsonschema_fill_default.py
jsonschema_fill_default-0.2.1.20250710.dist-info/LICENSE
jsonschema_fill_default-0.2.1.20250710.dist-info/METADATA
jsonschema_fill_default-0.2.1.20250710.dist-info/WHEEL
jsonschema_fill_default-0.2.1.20250710.dist-info/RECORD
