Metadata-Version: 2.3
Name: jsonschema-fill-default
Version: 0.2.1.20250710
Summary: Fill a JSON instance with the missing defaults from its JSON Schema Draft 2020-12-valid schema
License: MIT
Keywords: jsonschema,default,nested
Author: Lars Maxfield
Maintainer: Lars Maxfield
Requires-Python: >=3.9,<4.0
Classifier: License :: OSI Approved :: MIT License
Classifier: Programming Language :: Python :: 3
Classifier: Programming Language :: Python :: 3.9
Classifier: Programming Language :: Python :: 3.10
Classifier: Programming Language :: Python :: 3.11
Classifier: Programming Language :: Python :: 3.12
Classifier: Programming Language :: Python :: 3.13
Requires-Dist: jsonschema (>=4.23.0,<5.0.0)
Project-URL: Repository, https://github.com/larsmaxfield/jsonschema-fill-default
